next_python/__init__.py
next_python/database.py
next_python/decorators.py
next_python/docs.py
next_python/json.py
next_python/next.py
next_python/response.py
next_python/router.py
next_python/server.py
next_python/utils.py
next_python-0.0.1.dist-info/METADATA
next_python-0.0.1.dist-info/WHEEL
next_python-0.0.1.dist-info/RECORD
