Metadata-Version: 2.1
Name: next-python
Version: 0.0.1
Summary: 
Author: Oscar Bahamonde
Author-email: o.bahamonde@globant.com
Requires-Python: >=3.11,<4.0
Classifier: Programming Language :: Python :: 3
Classifier: Programming Language :: Python :: 3.11
Requires-Dist: aiohttp (>=3.8.6,<4.0.0)
Requires-Dist: aiohttp-sse (>=2.1.0,<3.0.0)
Requires-Dist: jinja2 (>=3.1.2,<4.0.0)
Requires-Dist: pydantic (==1.10.12)
Requires-Dist: rich (>=13.6.0,<14.0.0)
Requires-Dist: tenacity (>=8.2.3,<9.0.0)
